pygdtf/__init__.py
pygdtf/base_node.py
pygdtf/dmxbreak.py
pygdtf/geometries.py
pygdtf/macro.py
pygdtf/properties.py
pygdtf/protocols.py
pygdtf/revisions.py
pygdtf/value.py
pygdtf/utils/__init__.py
pygdtf/utils/attr_loader.py
pygdtf/utils/attribute_definitions_data.py
pygdtf/utils/attribute_regenerator.py
pygdtf-1.4.2.dist-info/licenses/LICENSE
pygdtf-1.4.2.dist-info/METADATA
pygdtf-1.4.2.dist-info/WHEEL
pygdtf-1.4.2.dist-info/top_level.txt
pygdtf-1.4.2.dist-info/RECORD
