Metadata-Version: 2.4
Name: pygdtf
Version: 1.4.2
Summary: General Device Type Format (GDTF) library for Python
Author: Jack Page
Author-email: vanous <noreply@nodomain.com>
Maintainer-email: vanous <noreply@nodomain.com>
Project-URL: Repository, https://github.com/open-stage/python-gdtf.git
Project-URL: Changelog, https://github.com/open-stage/python-gdtf/blob/master/CHANGELOG.md
Keywords: MVR,GDTF
Classifier: Development Status :: 4 - Beta
Classifier: Programming Language :: Python
Requires-Python: >=3.8
License-File: LICENSE
Dynamic: license-file
